bcsquants/__init__.py
bcsquants/backtest.py
bcsquants-0.1.0.dist-info/DESCRIPTION.rst
bcsquants-0.1.0.dist-info/METADATA
bcsquants-0.1.0.dist-info/RECORD
bcsquants-0.1.0.dist-info/WHEEL
bcsquants-0.1.0.dist-info/metadata.json
bcsquants-0.1.0.dist-info/top_level.txt
