Metadata-Version: 2.0
Name: bcsquants
Version: 0.1.0
Summary: BcsQuants localtest
Home-page: https://github.com/QuantForces/bcsquants
Author: Dmitrii Ivanovskii
Author-email: dima-iv@mail.ru
License: MIT
Keywords: quant backtest trading
Platform: UNKNOWN
Classifier: Development Status :: 3 - Alpha
Classifier: Intended Audience :: Developers
Classifier: Topic :: Software Development :: Build Tools
Classifier: License :: OSI Approved :: MIT License
Classifier: Programming Language :: Python :: 2
Classifier: Programming Language :: Python :: 2.6
Classifier: Programming Language :: Python :: 2.7
Classifier: Programming Language :: Python :: 3
Classifier: Programming Language :: Python :: 3.3
Classifier: Programming Language :: Python :: 3.4
Classifier: Programming Language :: Python :: 3.5
Requires-Dist: matplotlib
Requires-Dist: numpy
Requires-Dist: pandas
